<?xml version="1.0" encoding="utf-8"?>
<post>
  <title>Weer eens een verzamel aankoop</title>
  <slug>weer-eens-een-verzamel-aankoop</slug>
  <author>Jan</author>
  <pubDate>2008-01-07 20:09:00</pubDate>
  <lastModified>2014-04-25 12:06:08</lastModified>
  <content>&lt;div class="ExternalClassF6B33A12D6EF40E7BAC9DA9EDA02D579"&gt;Vandaag ben ik naar Amersfoort gereden, omdat daar een zaakje zit waar ze me waarschijnlijk nieuwe speakers en versterkers wilden verkopen.&lt;br /&gt;Uiteraard bleek dat ook het geval te zijn, maar tijdens het lopen van de parkeergarage naar die zaak zag ik ook de naam Nedgame boven een winkeltje staan.&lt;br /&gt;Dat is leuk, een goede game-zaak op m'n route. Deze kans kon ik natuurlijk niet onbenut raken, aangezien ik niet dagelijks in Amersfoort kom.&lt;br /&gt;&lt;br /&gt;Nadat ik enkele speakers had beluisterd ben ik naar Nedgame gegaan.&lt;br /&gt;Het viel me op dat het een behoorlijk klein winkeltje was met veel bezoekers.&lt;br /&gt;Het mooie aan deze winkel is dat ze ook nog oude games verkopen.&lt;br /&gt;Rekken vol met Playstation en Playstation 2 spellen, special editions van PC games, Gameboy Advance spellen, maar ook nog Dreamcast en de klassieke consoles.&lt;br /&gt;Aangezien m'n legale Dreamcast collectie behoorlijk karig is heb ik maar weer even wat ingeslagen.&lt;br /&gt;Nu heb ik weer 5 extra games voor dit platform er bij. Ook zag ik Final Fantasy Origins liggen. Nog wel prijzig, maar ach, het is als verzamelaar toch een schande dat ik deze titel nog niet in m'n bezit had.&lt;br /&gt;&lt;br /&gt;Dus weer een nutteloze aanschaf gedaan. Eigenlijk kon het niet meer deze maand, maar ja....&lt;br /&gt;&lt;img src="http://www.freezco.com/pics/digicam/HPIM0784_web.jpg" alt="" /&gt;&lt;/div&gt;</content>
  <ispublished>true</ispublished>
  <categories></categories>
  <comments></comments>
</post>